subana/__init__.py
subana/estimators.py
subana/evaluators/__init__.py
subana/evaluators/accuracy.py
subana/evaluators/interface.py
subana/evaluators/reconstruct.py
subana/feature_map_shape_normalizers/__init__.py
subana/feature_map_shape_normalizers/interface.py
subana/feature_map_shape_normalizers/mlps.py
subana/feature_map_shape_normalizers/vits.py
subana/foo.py
subana/intercepts.py
subana/utils/__init__.py
subana/utils/metrics.py
subana-0.0.3.dist-info/LICENSE
subana-0.0.3.dist-info/METADATA
subana-0.0.3.dist-info/WHEEL
subana-0.0.3.dist-info/RECORD
