Metadata-Version: 2.1
Name: subana
Version: 0.0.3
Summary: This is a template repository for Python projects that use Poetry for their dependency management.
Home-page: https://github.com/p16i/neural-subspace-analysis
Author: Pat Chormai
Author-email: pat.chormai@gmail.com
Requires-Python: >=3.11,<4.0
Classifier: Programming Language :: Python :: 3
Classifier: Programming Language :: Python :: 3.11
Classifier: Programming Language :: Python :: 3.12
Requires-Dist: numpy (>=2.3.1,<3.0.0)
Requires-Dist: pandas (>=2.3.1,<3.0.0)
Requires-Dist: scipy (>=1.16.0,<2.0.0)
Requires-Dist: torch (>=2.7.1,<3.0.0)
Requires-Dist: torchmetrics (>=1.8.0,<2.0.0)
Requires-Dist: torchvision (>=0.22.1,<0.23.0)
Requires-Dist: tqdm (>=4.67.1,<5.0.0)
Project-URL: Documentation, https://p16i.github.io/neural-subspace-analysis/
Project-URL: Repository, https://github.com/p16i/neural-subspace-analysis
